noid/__init__.py
noid/cli.py
noid/noid.cfg
noid/pynoid.py
noid/utils.py
noid-1.1.3.dist-info/METADATA
noid-1.1.3.dist-info/WHEEL
noid-1.1.3.dist-info/entry_points.txt
noid-1.1.3.dist-info/top_level.txt
noid-1.1.3.dist-info/RECORD
