Metadata-Version: 2.1
Name: noid
Version: 1.1.3
Summary: Mint NOIDs using a CLI or API
Home-page: https://github.com/paulkorir/noid
Author: Paul K. Korir
Author-email: pkorir@ebi.ac.uk, paulkorir@gmail.com
License: MIT
Classifier: Programming Language :: Python :: 3
Classifier: Programming Language :: Python :: 3.6
Classifier: Programming Language :: Python :: 3.7
Classifier: Programming Language :: Python :: 3.8
Classifier: Programming Language :: Python :: 3.9
Classifier: Programming Language :: Python :: 3.10
Classifier: License :: OSI Approved :: MIT License
Classifier: Operating System :: OS Independent
